setup.py
darner/__init__.py
darner/client.py
pydarner.egg-info/PKG-INFO
pydarner.egg-info/SOURCES.txt
pydarner.egg-info/dependency_links.txt
pydarner.egg-info/requires.txt
pydarner.egg-info/top_level.txt
pydarner.egg-info/zip-safe