Metadata-Version: 1.1
Name: pydarner
Version: 0.0.5
Summary: A python darner client
Home-page: https://github.com/siqueries/pydarner
Author: Ebot Tabi
Author-email: ebottabi@siqueries.com
License: BSD
Download-URL: https://github.com/siqueries/pydarner/tarball/0.0.5
Keywords: queues darner memcached
Platform: UNKNOWN
Classifier: Development Status :: 3 - Alpha
Classifier: Intended Audience :: Developers
Classifier: Intended Audience :: System Administrators
Classifier: Programming Language :: Python
